{"updated": "2026-04-30T09:52:03Z", "quotes": [{"symbol": "ACS.MC", "price": 120.6, "changePct": 1.17, "high52": 125.1, "low52": 54.65, "pe": null, "marketCap": 31417592675, "ma200": 84.952}, {"symbol": "IBE.MC", "price": 19.86, "changePct": -0.7, "high52": 20.6, "low52": 15.03, "pe": null, "marketCap": 134210817820, "ma200": 17.855}, {"symbol": "VIS.MC", "price": 59.7, "changePct": -0.67, "high52": 65.2, "low52": 48.35, "pe": null, "marketCap": 2703235675, "ma200": 57.017}, {"symbol": "LOG.MC", "price": 32.9, "changePct": -0.06, "high52": 34.48, "low52": 26.84, "pe": null, "marketCap": 4346728165, "ma200": 30.085}, {"symbol": "VID.MC", "price": 77.0, "changePct": 0.39, "high52": 100.6, "low52": 70.4, "pe": null, "marketCap": 2683765084, "ma200": 86.305}, {"symbol": "REP.MC", "price": 22.16, "changePct": 0.82, "high52": 24.9, "low52": 10.58, "pe": null, "marketCap": 24407254229, "ma200": 16.785}, {"symbol": "TRE.MC", "price": 34.1, "changePct": -2.63, "high52": 38.66, "low52": 14.86, "pe": null, "marketCap": 2663107887, "ma200": 28.563}, {"symbol": "IDR.MC", "price": 48.5, "changePct": -0.9, "high52": 66.15, "low52": 28.04, "pe": null, "marketCap": 8487196293, "ma200": 46.415}, {"symbol": "ENG.MC", "price": 16.98, "changePct": 0.3, "high52": 17.37, "low52": 13.0, "pe": null, "marketCap": 4413826468, "ma200": 14.186}, {"symbol": "EBRO.MC", "price": 18.08, "changePct": -1.63, "high52": 19.64, "low52": 16.8, "pe": null, "marketCap": 2781886275, "ma200": 18.195}, {"symbol": "MCM.MC", "price": 13.9, "changePct": -0.36, "high52": 15.0, "low52": 13.0, "pe": null, "marketCap": 520584064, "ma200": 14.137}, {"symbol": "ANA.MC", "price": 240.4, "changePct": 0.5, "high52": 260.0, "low52": 122.6, "pe": null, "marketCap": 13103017293, "ma200": 190.108}, {"symbol": "ITX.MC", "price": 50.2, "changePct": -0.63, "high52": 58.28, "low52": 40.8, "pe": null, "marketCap": 156405708681, "ma200": 50.047}, {"symbol": "CBAV.MC", "price": 55.0, "changePct": 1.48, "high52": 56.6, "low52": 36.0, "pe": null, "marketCap": 881018270, "ma200": 46.928}, {"symbol": "RED.MC", "price": 14.85, "changePct": 0.07, "high52": 18.75, "low52": 14.15, "pe": null, "marketCap": 8025059882, "ma200": 15.688}, {"symbol": "ACX.MC", "price": 13.72, "changePct": 2.69, "high52": 14.1, "low52": 9.755, "pe": null, "marketCap": 3420785316, "ma200": 11.948}, {"symbol": "BBVA.MC", "price": 18.575, "changePct": -0.05, "high52": 22.33, "low52": 12.04, "pe": null, "marketCap": 103670878031, "ma200": 17.954}, {"symbol": "GEST.MC", "price": 3.175, "changePct": 0.16, "high52": 3.542, "low52": 2.538, "pe": null, "marketCap": 1806156438, "ma200": 3.16}, {"symbol": "NTGY.MC", "price": 26.9, "changePct": 0.9, "high52": 27.96, "low52": 24.3, "pe": null, "marketCap": 24919986706, "ma200": 26.317}]}